{
    "geode": "4.8.0",
    "gd": {
        "win": "2.2074",
        "android": "2.2074",
        "mac": "2.2074",
        "ios": "2.2074"
    },

    "version": "v1.0.0",
    "id": "undefined0.socials_integration",
    "name": "Socials Integration",
    "developer": "undefined0",
    "description": "Lets you invite friends from Steam into levels and Globed rooms!",
    "tags": [ "online" ],

    "dependencies": {
        "geode.node-ids": {
            "importance": "required",
            "version": "v1.21.0"
        }
    },

    "resources": {
        "sprites": [ "resources/*.png" ]
    },

    "links": {
        "source": "https://github.com/undefined06855/socials-integration"
    }
}
 